{
  "HALProvider": {
    "Other Devices": {
      "SPARK MAX [10]": {
        "header": {
          "open": true
        }
      },
      "SPARK MAX [6]": {
        "header": {
          "open": true
        }
      },
      "SPARK MAX [7]": {
        "header": {
          "open": true
        }
      },
      "Victor SPX[0]": {
        "header": {
          "open": true
        }
      },
      "Victor SPX[1]": {
        "header": {
          "open": true
        }
      },
      "Victor SPX[2]": {
        "header": {
          "open": true
        }
      },
      "Victor SPX[3]": {
        "header": {
          "open": true
        }
      },
      "navX-Sensor[0]": {
        "header": {
          "open": true
        }
      }
    }
  },
  "NTProvider": {
    "types": {
      "/FMSInfo": "FMSInfo",
      "/LiveWindow/Arm": "Subsystem",
      "/LiveWindow/ArmSystem": "Subsystem",
      "/LiveWindow/Climber": "Subsystem",
      "/LiveWindow/Drivetrain": "Subsystem",
      "/LiveWindow/Intake": "Subsystem",
      "/LiveWindow/Launcher": "Subsystem",
      "/LiveWindow/Scooper": "Subsystem",
      "/LiveWindow/Ungrouped/DifferentialDrive[1]": "DifferentialDrive",
      "/LiveWindow/Ungrouped/Scheduler": "Scheduler",
      "/LiveWindow/Ungrouped/Victor SPX [1]": "Motor Controller",
      "/LiveWindow/Ungrouped/Victor SPX [3]": "Motor Controller",
      "/LiveWindow/Ungrouped/navX-Sensor[4]": "Gyro",
      "/SmartDashboard/Arm": "Subsystem",
      "/SmartDashboard/ArmSystem": "Subsystem",
      "/SmartDashboard/Auto Mode": "String Chooser",
      "/SmartDashboard/Auton": "String Chooser",
      "/SmartDashboard/Autonomous Command": "Command",
      "/SmartDashboard/Climber": "Subsystem",
      "/SmartDashboard/Drivetrain": "Subsystem",
      "/SmartDashboard/Launcher": "Subsystem",
      "/SmartDashboard/Scooper": "Subsystem",
      "/SmartDashboard/Scooper_command": "Command"
    }
  },
  "NetworkTables": {
    "SmartDashboard": {
      "Drivetrain": {
        "open": true
      },
      "open": true
    }
  }
}
